Metadata-Version: 2.1
Name: uxtools
Version: 0.1.0
Summary: My short description for my project.
Home-page: https://github.com/qu6zhi/uxtools
Author: qu6zhi
Author-email: qu6zhi@qq.com
License: MIT
Classifier: License :: OSI Approved :: MIT License
Classifier: Programming Language :: Python
Classifier: Programming Language :: Python :: 3
Classifier: Programming Language :: Python :: 3.6
Classifier: Programming Language :: Python :: Implementation :: CPython
Classifier: Programming Language :: Python :: Implementation :: PyPy
Requires-Python: >=3.6.0
License-File: LICENSE
